crypto_gpu_lib/__init__.py
crypto_gpu_lib/core.py
crypto_gpu_lib/cuda_engine.py
crypto_gpu_lib/fast_core.py
crypto_gpu_lib/gpu_crypto.py
crypto_gpu_lib/networks.py
crypto_gpu_lib/ultra_fast_crypto.py
crypto_gpu_lib/utils.py
crypto_gpu_lib-1.0.7.dist-info/licenses/LICENSE
crypto_gpu_lib-1.0.7.dist-info/METADATA
crypto_gpu_lib-1.0.7.dist-info/WHEEL
crypto_gpu_lib-1.0.7.dist-info/top_level.txt
crypto_gpu_lib-1.0.7.dist-info/RECORD
