Metadata-Version: 2.4
Name: crypto-gpu-lib
Version: 1.0.7
Summary: High-performance GPU-accelerated cryptocurrency wallet generation library
Home-page: https://github.com/cryptogpu/crypto-gpu-lib
Author: CryptoGPU Team
Author-email: team@cryptogpu.dev
Project-URL: Homepage, https://github.com/cryptogpu/crypto-gpu-lib
Project-URL: Bug Reports, https://github.com/cryptogpu/crypto-gpu-lib/issues
Project-URL: Source, https://github.com/cryptogpu/crypto-gpu-lib
Project-URL: Documentation, https://github.com/cryptogpu/crypto-gpu-lib#readme
Keywords: cryptocurrency,wallet,gpu,cuda,bitcoin,ethereum,blockchain,bip39,bip44
Classifier: Development Status :: 4 - Beta
Classifier: Intended Audience :: Developers
Classifier: Intended Audience :: Financial and Insurance Industry
Classifier: License :: OSI Approved :: MIT License
Classifier: Operating System :: OS Independent
Classifier: Programming Language :: Python :: 3
Classifier: Programming Language :: Python :: 3.8
Classifier: Programming Language :: Python :: 3.9
Classifier: Programming Language :: Python :: 3.10
Classifier: Programming Language :: Python :: 3.11
Classifier: Topic :: Software Development :: Libraries :: Python Modules
Classifier: Topic :: Security :: Cryptography
Classifier: Topic :: Office/Business :: Financial
Requires-Python: >=3.8
License-File: LICENSE
Requires-Dist: numpy>=1.21.0
Requires-Dist: mnemonic>=0.20
Requires-Dist: hdwallet>=2.2.1
Requires-Dist: eth-account>=0.8.0
Requires-Dist: ecdsa>=0.18.0
Requires-Dist: base58>=2.1.1
Requires-Dist: pycryptodome>=3.15.0
Requires-Dist: solders>=0.18.0
Requires-Dist: aiohttp>=3.8.0
Requires-Dist: requests>=2.28.0
Requires-Dist: psutil>=5.9.0
Provides-Extra: gpu
Requires-Dist: cupy-cuda12x>=12.0.0; extra == "gpu"
Provides-Extra: dev
Requires-Dist: pytest>=7.0.0; extra == "dev"
Requires-Dist: black>=22.0.0; extra == "dev"
Requires-Dist: flake8>=4.0.0; extra == "dev"
Requires-Dist: mypy>=0.950; extra == "dev"
Requires-Dist: bandit>=1.7.0; extra == "dev"
Requires-Dist: safety>=2.0.0; extra == "dev"
Provides-Extra: torch
Requires-Dist: torch>=2.0.0; extra == "torch"
Provides-Extra: all
Requires-Dist: cupy-cuda12x>=12.0.0; extra == "all"
Requires-Dist: torch>=2.0.0; extra == "all"
Requires-Dist: pytest>=7.0.0; extra == "all"
Requires-Dist: black>=22.0.0; extra == "all"
Requires-Dist: flake8>=4.0.0; extra == "all"
Requires-Dist: mypy>=0.950; extra == "all"
Requires-Dist: bandit>=1.7.0; extra == "all"
Requires-Dist: safety>=2.0.0; extra == "all"
Dynamic: author
Dynamic: author-email
Dynamic: classifier
Dynamic: description
Dynamic: description-content-type
Dynamic: home-page
Dynamic: keywords
Dynamic: license-file
Dynamic: project-url
Dynamic: provides-extra
Dynamic: requires-dist
Dynamic: requires-python
Dynamic: summary
